Workbook

Sheet Annotation Tracker
A1: TWEET INFO | E1: ANNOTATOR 1 | H1: ANNOTATOR 2 | K1: RESOLUTION | O1: PIPELINE INPUT
A2: ID | B2: Tweet Text (Spanish) | C2: URL | D2: Topic Area | E2: A1 Label | F2: A1 Confidence (1-3) | G2: A1 Rationale / Source | H2: A2 Label | I2: A2 Confidence (1-3) | J2: A2 Rationale / Source | K2: Agreement? (Y/N) | L2: Gold Label | M2: Disagree Code | N2: Notes / Flags | O2: MT Translation (EN) | P2: Pipeline Prediction
A3: ES-01 | B3: La ciencia es contundente: tras analizar a más de 1.3 millones de niños, se confirma que no existe vínculo entre las vacunas y el autismo. 🧬 La desinformación confunde coincidencias temporales con causalidad. ¡Las vacunas salvan vidas y son seguras! 🛡️✨ #Ciencia #Vacunas | C3: https://x.com/BondzuCubs/status/2063670312462405976 | D3: Vaccines | E3: =TRUE() -> TRUE | F3: 3 | G3: e.g. Taylor et al. (2002), Madsen et al. (2002), or the 2019 Hviid et al. meta-analysis of 650,000+ Danish children — all find no MMR-autism link. Claim is directionally accurate. | H3: =TRUE() -> TRUE | I3: 3 | J3: Multiple large-scale meta-analyses (incl. Hviid et al. 2019, 650k+ children) confirm no MMR–autism link | K3: Y | L3: TRUE | M3: - | N3: Tweet mixes verifiable factual claim with editorial framing ("La desinformación confunde…"). Core claim annotated, not the opinion. The 1.3M figure likely refers to the 2019 Hviid et al. study (~650K) or a pooled estimate,slightly imprecise but not substantially wrong per rule 4.5. | O3: The science is conclusive: after analyzing more than 1.3 million children, it's confirmed that there is no link between vaccines and autism. 🧬 Misinformation confuses temporal coincidences with causality. Vaccines save lives and are safe! 🛡️✨ #Science #Vaccines
A4: ES-02 | B4: ATENCION: Las vacunas que contienen mercurio (timerosal) causan autismo...Los reguladores de vacunas ya lo sabían en 1999 y lo saben a día de hoy ... Robert F Kennedy Jr. ¿Más EVIDENCIA de que las vacunas causan autismo? http://ncbi.nlm.nih.gov/pmc/articles/PMC3878266/ | C4: https://x.com/Fa21519230/status/1933929795319910721 | D4: Vaccines | E4: =FALSE() -> FALSE | F4: 3 | G4: Thimerosal-autism claim contradicts scientific consensus. Removed from most vaccines in 2001; autism rates continued rising afterwards, disconfirming the hypothesis. WHO, CDC, and multiple large-scale studies find no causal link. Linked PubMed article (PMC3878266) is a real but heavily criticised outlier, does not represent consensus. | H4: =FALSE() -> FALSE | I4: 3 | J4: Thimerosal autism hypothesis contradicts consensus; autism rates continued rising after thimerosal removal from most vaccines in 2001 (WHO, CDC). | K4: Y | L4: FALSE | M4: - | N4: Tweet includes pubmed link, might confuse pipeline | O4: WARNING: Vaccines containing mercury (thimerosal) cause autism...Vaccine regulators knew this in 1999 and still know it today... Robert F. Kennedy Jr. More EVIDENCE that vaccines cause autism? http://ncbi.nlm.nih.gov/pmc/articles/PMC3878266/
A5: ES-03 | B5: A fecha 24 de septiembre de 2025 y continua la EPIDEMIA de extraños coágulos blancos fibrosos, relacionados con las "vacunas" COVID...Taponan venas y arterias de "vacunados" y han podido causar un tsunami de muertes súbitas desde 2021. John Olooney, director de funeraria. | C5: https://x.com/Fa21519230/status/2061459993694519576 | D5: Vaccines | E5: =FALSE() -> FALSE | F5: 3 | G5: Claims of fibrous clot epidemic and vaccine-caused mass sudden deaths contradict scientific consensus. Source cited is a funeral director, not peer-reviewed. Partial truth noted: rare VITT clotting is documented for AstraZeneca but massively overstated here. | H5: =FALSE() -> FALSE | I5: 3 | J5: No peer-reviewed evidence for a fibrous-clot epidemic or vaccine-caused mass sudden deaths; only source cited is a funeral director, not scientific literature. | K5: Y | L5: FALSE | M5: - | N5: [DATE: 2025-09-24] Partial truth: rare VITT clotting known for AstraZeneca but claim vastly overstated. Scare quotes around "vacunas" signal distrust, not sarcasm — claim still asserted as fact. Non-scientific source (funeral director). | O5: As of September 24, 2025, the epidemic of strange, white, fibrous clots linked to COVID "vaccines" continues... They clog the veins and arteries of vaccinated individuals and may have caused a tsunami of sudden deaths since 2021. John Olooney, Funeral Director.
A6: ES-04 | B6: En 1891, el Dr. J. Collins Warren publicaba en el Boston Medical and Surgical Journal un artículo titulado "The Parasitic Origin of Cancer"... Investigadores, entre ellos el Dr. Weber, han filmado al microscopio lo que llaman micro-parásitos presentes en los tejidos de todos los pacientes con cáncer... La medicina oficial los llama "orgánulos celulares" o "vesículas atípicas"... Pero estos «orgánulos» se mueven activamente… y sobreviven incluso cuando la célula muere. Dr. Lee Merritt: "Saben que el cáncer es causado por parásitos, pero no quieren que se sepa… porque perderían su financiación". | C6: https://x.com/elzorrotacneno/status/2062698756710293547 | D6: Cancer | E6: =FALSE() -> FALSE | F6: 3 | G6: Universal parasitic causation of cancer contradicts scientific consensus. Some parasites raise cancer risk in specific contexts but this is not the same claim. The 1891 Warren article is real but a long-abandoned hypothesis. Lee Merritt is a known misinformation figure, not an oncology researcher. Moving "orgánulos" are standard cell biology (e.g. mitochondria, exosomes). | H6: =FALSE() -> FALSE | I6: 3 | J6: Universal parasitic causation of cancer contradicts oncology consensus; 'moving organelles' are standard cell biology (mitochondria, exosomes); Lee Merritt is a known misinformation figure. | K6: Y | L6: FALSE | M6: - | N6: Partial truth: some parasites (e.g. Schistosoma haematobium) are established cancer risk factors — note per §4.2, dominant claim is FALSE. Historical legitimacy framing (1891 article) does not validate the claim. Non-scientific source (Lee Merritt). Conspiracy framing ("no quieren que se sepa"). | O6: In 1891, Dr. J. Collins Warren published an article in the Boston Medical and Surgical Journal entitled "The Parasitic Origin of Cancer"... Researchers, including Dr. Weber, have filmed under a microscope what they call micro-parasites present in the tissues of all cancer patients... Mainstream medicine calls them "cell organelles" or "atypical vesicles"... But these "organelles" move actively... and survive even when the cell dies. Dr. Lee Merritt: "They know that cancer is caused by parasites, but they don't want it to be known... because they would lose their funding."
A7: ES-05 | B7: El veneno de abeja ha demostrado capacidad para matar células cancerosas al destruir su membrana y desencadenar apoptosis (muerte celular programada). Este efecto selectivo lo convierte en un potencial aliado contra el cáncer. | C7: https://x.com/Bio_comunidad/status/1829665809720832194 | D7: Cancer | E7: =FALSE() -> FALSE | F7: 3 | G7: The tweet is false because while bee venom shows some anti-cancer effects in laboratory and animal studies, it has never been tested in human clinical trials, is not an approved treatment, and its claimed "selective" effect on cancer cells is misleading — it can also damage healthy tissue and trigger severe allergic reactions. | H7: UNVERIFIABLE | I7: 2 | J7: Melittin has real in vitro cytotoxic effects (e.g. Nature Precision Oncology 2020), but 'ha demostrado' overstates early-stage preclinical research as established clinical fact. | K7: N | L7: UNVERIFIABLE | M7: EVIDENCE | N7: Partial truth: in vitro evidence for melittin cytotoxicity is real but "ha demostrado" and "efecto selectivo" overstate clinical validity per §4.2. No source cited per §5.9 — figure/claim unverifiable without reference. Likely annotator disagreement between UNVERIFIABLE and TRUE. [OVERSTATEMENT-OF-EVIDENCE] | O7: Bee venom has demonstrated the ability to kill cancer cells by destroying their membranes and triggering apoptosis (programmed cell death). This selective effect makes it a potential ally against cancer.
A8: ES-06 | B8: Hay un test de sangre llamado Galleri que detecta cáncer antes de que dé síntomas. La clave: toda célula que muere libera fragmentos de ADN al torrente sanguíneo, y las cancerígenas dejan una huella molecular distinta. El test reconoce esa huella en una muestra. #deteccionCancer | C8: https://x.com/carlodelasancha/status/2063727700628603071 | D8: Cancer | E8: =TRUE() -> TRUE | F8: 3 | G8: Galleri is a real MCED blood test by GRAIL. The cfDNA mechanism and cancer methylation signature are accurately described and supported by peer-reviewed literature. Claim is appropriately hedged ("antes de que dé síntomas"). No overclaiming. | H8: =TRUE() -> TRUE | I8: 3 | J8: Galleri (GRAIL) is a real MCED blood test; DNA cancer methylation signature mechanism is accurately described and supported by peer-reviewed literature. | K8: Y | L8: TRUE | M8: - | N8: Hashtag #deteccionCancer kept in column B per §5.3 — does not affect label. URL is hashtag link. | O8: There's a blood test called Galleri that detects cancer before symptoms appear. The key: every dying cell releases fragments of DNA into the bloodstream, and cancerous cells leave a distinct molecular signature. The test recognizes this signature in a sample. #CancerDetection
A9: ES-07 | B9: 🚨🚨Florida PROHÍBE la carne falsa de Bill Gates, 'causa cáncer' 👏 Un estudio REVELA que la carne falsa de Bill Gates causa 'turbocánceres' en humanos. La Élite Globalista en el WEF están promoviendo fuertemente la carne sintética como la "solución al llamado "Cambio Climático" ahora se ha demostrado que la CARNE FALSA DE BILL GATES CAUSA CÁNCER. Por eso están eliminando la agricultura y la ganadería para que no te quede otra opción que la carne falsa de Bill Gates ⚔️🔥 👇 https://thepeoplesvoice.tv/florida-set-to-ban-bill-gates-fake-meat-it-causes-cancer/ | C9: https://x.com/dejanirasilveir/status/1839726477849375107 | D9: Food Science | E9: =FALSE() -> FALSE | F9: 3 | G9: No peer-reviewed evidence that cultivated meat causes cancer or "turbo cancers". The People's Voice is a known misinformation outlet. Florida's lab-grown meat ban is real but not on cancer grounds. Conspiracy framing (Bill Gates, WEF, globalist elite) does not constitute scientific evidence. | H9: =FALSE() -> FALSE | I9: 3 | J9: No scientific evidence that cultivated meat causes cancer or 'turbo cancers'; The People's Voice is a known misinformation outlet; Florida's ban is real but not based on cancer evidence. | K9: Y | L9: FALSE | M9: - | N9: URL source is The People's Voice, a known misinformation outlet — annotating tweet text only per §5.1, [LINK-DEPENDENT] not needed as claim is self-contained. Partial truth: Florida ban on lab-grown meat is real but not justified on cancer grounds — dominant claim FALSE per §4.2. Conspiracy framing (Gates, WEF). [TROJAN-HORSE] | O9: 🚨🚨Florida BANS Bill Gates' fake meat, 'it causes cancer' 👏 A study REVEALS that Bill Gates' fake meat causes 'turbocancers' in humans. The Globalist Elite at the WEF are heavily promoting synthetic meat as the "solution to so-called "Climate Change" now BILL GATES' FAKE MEAT has been proven to CAUSE CANCER. That's why they are eliminating agriculture and livestock so that you have no other option than Bill Gates' fake meat ⚔️🔥 👇 https://thepeoplesvoice.tv/florida-set-to-ban-bill-gates-fake-meat-it-causes-cancer/
A10: ES-08 | B10: 🚨🚨 Este médico explica qué le hizo exactamente cada "vacuna* contra COVID a tu sistema inmunológico y por qué se administraban cada 8 semanas.... Sabían exactamente lo que estaban haciendo... ▪️ Primera inyección: reduce la producción de glóbulos blancos en un 50 %... ▪️ El sistema inmunológico comienza a recuperarse lentamente... ▪️ 8 semanas después: la segunda dosis llega mientras aún estás caído... ▪️Esta vez menos salina, más carga tóxica... Ahora su defensa inmunológica está debilitada y su sistema no puede recuperarse como está diseñado... Esto no es medicina. Es ingeniería: atacar tu inmunidad en oleadas calculadas... | C10: https://x.com/Fa21519230/status/2063356348071641329 | D10: Vaccines | E10: =FALSE() -> FALSE | F10: 3 | G10: No evidence COVID vaccines reduce white blood cell production by 50%. No evidence of deliberate immune suppression by design. Dosing intervals were based on immunogenicity data, not exploitation of immune weakness. Claim contradicts scientific consensus on vaccine safety and mechanism. | H10: =FALSE() -> FALSE | I10: 3 | J10: No evidence that COVID vaccines reduce white blood cell production by 50%; dosing intervals were based on immunogenicity data, not deliberate immune suppression — contradicts scientific consensus. | K10: Y | L10: FALSE | M10: - | N10: Numerical claim "50%" per §4.5 — substantially wrong, label unaffected. No named source ("este médico" is anonymous). Conspiracy framing ("sabían exactamente lo que estaban haciendo"). Scare quotes around "vacuna" signal distrust, not sarcasm. | O10: 🚨🚨 This doctor explains exactly what each COVID "vaccine" did to your immune system and why they were administered every 8 weeks... They knew exactly what they were doing... ▪️ First injection: reduces white blood cell production by 50%... ▪️ The immune system slowly begins to recover... ▪️ 8 weeks later: the second dose arrives while you're still down... ▪️ This time less saline, more toxic load... Now your immune defense is weakened and your system can't recover as it's designed to... This isn't medicine. It's engineering: attacking your immunity in calculated waves...
A11: ES-09 | B11: 🚨 C*NC*R DE PRÓSTATA EN ESTADIO 4 — DIAGNÓSTICO TERMINAL VENCIDO SIN QUIMIOTERAPIA! ESTE HOMBRE ES LA PRUEBA VIVA EN 2026! Los médicos le dijeron que solo le quedaban 10 meses de vida. C*nc*r de próstata en estadio 4. Sin esperanza sin quimioterapia. Él se negó. En cambio, recurrió al Dióxido de Cloro (oral + intravenoso) combinado con enemas diarios de CD, más autocuidado y nutrición para limpiar y oxigenar su cuerpo. ¿Hoy? Está sano, fuerte y libre de c*nc*r. Esta es una historia tan increíble —del tipo que el establecimiento médico no quiere que veas. El dióxido de cloro oxida y destruye lo que no pertenece… mientras que la comida real y el autocuidado reconstruyen lo que sí. Sin veneno. Sin radiación. Solo resultados. Esto podría ser el remedio que han estado ocultando para TODAS las enfermedades. Compártelo con alguien que esté luchando contra el cáncer. La verdad se está extendiendo en 2026. Reza por cada guerrero ahí fuera. Toma el control de tu propia salud. | C11: https://x.com/EmpiezaHoyYa/status/2063198535252586570 | D11: Cancer | E11: =FALSE() -> FALSE | F11: 3 | G11: Chlorine dioxide has no peer-reviewed evidence as a cancer treatment. It is classified as a dangerous bleaching agent by the FDA and WHO. Single anecdotal case does not constitute scientific evidence. Claim that it cures all diseases directly contradicts scientific consensus. | H11: =FALSE() -> FALSE | I11: 3 | J11: Chlorine dioxide has no peer-reviewed evidence as a cancer treatment; FDA and WHO classify it as a dangerous industrial bleach; single anecdote cannot establish efficacy. | K11: Y | L11: FALSE | M11: - | N11: Anecdotal single case generalised to universal cure per §4.4 — dominant claim still FALSE not UNVERIFIABLE as chlorine dioxide is actively contraindicated by scientific consensus. Self-censored spelling (C*NC*R) per §4.6 — interpreted charitably as "cáncer". Conspiracy framing ("el establecimiento médico no quiere que veas"). [HISTORICAL-APPEAL] | O11: 🚨 STAGE 4 PROSTATE CANCER — TERMINALLY OVERCOME WITHOUT CHEMOTHERAPY! THIS MAN IS LIVING PROOF IN 2026! Doctors told him he only had 10 months to live. Stage 4 prostate cancer. No hope without chemotherapy. He refused. Instead, he turned to Chlorine Dioxide (oral + intravenous) combined with daily CD enemas, plus self-care and nutrition to cleanse and oxygenate his body. Today? He is healthy, strong, and cancer-free. This is such an incredible story—the kind the medical establishment doesn't want you to see. Chlorine dioxide oxidizes and destroys what doesn't belong… while real food and self-care rebuild what does. No poison. No radiation. Just results. This could be the cure they've been hiding for ALL diseases. Share it with someone battling cancer. The truth is spreading in 2026. Pray for every warrior out there. Take control of your own health.
A12: ES-10 | B12: Antes de los laboratorios modernos, la penicilina se obtenía de forma natural a partir del moho que crece en frutas como la naranja o el pan viejo. Ese moho pertenece al género Penicillium, el mismo que Alexander Fleming descubrió por accidente en 1928. En tiempos antiguos, algunos curanderos ya aplicaban este tipo de hongos sobre heridas infectadas, observando su poder para detener infecciones. Recuerda que la naturaleza fue siempre la primera farmacia de la humanidad. | C12: https://x.com/elzorrotacneno/status/2063093978115801499 | D12: Medicine | E12: =TRUE() -> TRUE | F12: 3 | G12: Fleming's 1928 discovery of Penicillium mould is historically accurate. The genus Penicillium does grow on citrus and bread. Historical use of moulds on wounds by ancient healers is documented in archaeological and historical literature. | H12: =TRUE() -> TRUE | I12: 2 | J12: Fleming's 1928 Penicillium discovery and its growth on bread/citrus are historically accurate; ancient use of moulds on infected wounds is documented in archaeological literature. | K12: Y | L12: TRUE | M12: - | N12: Confidence 2 not 3: "algunos curanderos ya aplicaban este tipo de hongos" is historically plausible but not precisely verifiable — annotator 2 may lean UNVERIFIABLE on this sub-claim. Final sentence ("la naturaleza fue siempre la primera farmacia") is opinion per §2, disregarded for labelling. Dominant claim TRUE per §4.2. | O12: Before modern laboratories, penicillin was obtained naturally from the mold that grows on fruits like oranges or stale bread. This mold belongs to the genus Penicillium, the same one Alexander Fleming discovered by accident in 1928. In ancient times, some healers applied this type of fungus to infected wounds, observing its power to stop infections. Remember that nature has always been humanity's first pharmacy.
A13: ES-11 | B13: 🚨 ÚLTIMA HORA: El fenbendazol se relaciona con la remisión o casi remisión en tres pacientes con cáncer en estadio IV... Nuevo estudio informa que pacientes con cáncer de mama, próstata y melanoma experimentaron una regresión tumoral drástica y una remisión duradera, sin quimioterapia 👇 ✅ Caso 1: Mujer de 83 años, estadio IV de mama → Remisión completa (3 años) ✅ Caso 2: Hombre de 75 años, próstata en estadio IV → Remisión casi completa (26 meses, PSA indetectable) ✅ Caso 3: Hombre de 63 años, melanoma en estadio IV → Remisión completa (11 meses) Los resultados reflejan los hallazgos preclínicos sobre la actividad anticancerígena del fenbendazol. Al igual que la ivermectina, el fenbendazol puede actuar como un potente agente anticancerígeno... https://t.co/miLzBe4bzI | C13: https://x.com/Fa21519230/status/1958163563425493015 | D13: Cancer | E13: UNVERIFIABLE | F13: 2 | G13: Fenbendazole does have real preclinical anticancer activity in cell and animal studies. A small case series of 3 patients exists in the literature. However 3 cases without controls cannot establish causation. "ÚLTIMA HORA" framing overstates a very preliminary case report as breakthrough evidence. Cannot verify or refute the specific claims without accessing the linked study, which is not permitted per §5.1. | H13: UNVERIFIABLE | I13: 2 | J13: Fenbendazole has real preclinical anticancer activity; a small case series exists, but 3 cases without controls cannot establish causation, and the specific study cannot be verified without accessing the link. | K13: Y | L13: UNVERIFIABLE | M13: - | N13: URL present per §5.1 — annotating tweet text only, [LINK-DEPENDENT] applies as specific case data cannot be verified without the linked study. Partial truth: fenbendazole preclinical anticancer activity is real per §4.2. 3-patient case series is insufficient to establish efficacy — overclaiming framing. Ivermectin comparison adds further misinformation signal. [OVERSTATEMENT-OF-EVIDENCE] | O13: 🚨 BREAKING NEWS: Fenbendazole is linked to remission or near-remission in three patients with stage IV cancer... A new study reports that patients with breast, prostate, and melanoma cancers experienced dramatic tumor regression and long-lasting remission without chemotherapy 👇 ✅ Case 1: 83-year-old woman, stage IV breast cancer → Complete remission (3 years) ✅ Case 2: 75-year-old man, stage IV prostate cancer → Near-complete remission (26 months, undetectable PSA) ✅ Case 3: 63-year-old man, stage IV melanoma → Complete remission (11 months) The results reflect preclinical findings on the anticancer activity of fenbendazole. Like ivermectin, fenbendazole may act as a potent anticancer agent... https://t.co/miLzBe4bzI
A14: ES-12 | B14: Es uno de los avances más fuertes en cáncer pancreático metastásico: daraxonrasib casi duplicó la supervivencia global frente a quimioterapia en pacientes ya tratados: 13,2 vs 6,6 meses. En un tumor donde ganar meses suele ser difícil, este resultado pesa muchísimo. | C14: https://x.com/drteoa/status/2061455281888854118 | D14: Cancer | E14: =TRUE() -> TRUE | F14: 3 | G14: Daraxonrasib (RMC-6236) is a real KRAS inhibitor in clinical trials. The 13.2 vs 6.6 month overall survival figures match data presented at ASCO 2025 for metastatic pancreatic cancer in previously treated patients. Framing is appropriately hedged ("uno de los avances más fuertes", "este resultado pesa muchísimo"). | H14: =TRUE() -> TRUE | I14: 3 | J14: Daraxonrasib OS data (13.2 vs 6.6 months) in previously treated metastatic pancreatic cancer matches data presented at ASCO 2025 for this KRAS inhibitor. | K14: Y | L14: TRUE | M14: - | N14: Numerical claim per §4.5 — 13.2 vs 6.6 months matches published trial data, within acceptable margin. No conspiracy framing. Appropriately hedged language. Good contrast with FALSE vaccine tweets in dataset. | O14: It is one of the most significant advances in metastatic pancreatic cancer: daraxonrasib nearly doubled overall survival compared to chemotherapy in previously treated patients: 13.2 vs. 6.6 months. In a tumor where gaining even a few months is often difficult, this result carries immense weight.
A15: ES-13 | B15: 🟧Existe una variabilidad significativa en la eficacia y seguridad de los iP2Y12 orales. El ticagrelor y el prasugrel tienen un inicio y un final de acción rápidos, proporcionan una inhibición plaquetaria más rápida, potente y predecible que el clopidogrel. 🤔💊 🔶La resistencia al clopidogrel es un fenómeno clínico bien conocido, caracterizado por una elevada reactividad plaquetaria residual. Esta variabilidad en la respuesta afecta hasta 1/3 de los 👥 tratados con clopidogrel y se asocia a un mayor riesgo de eventos trombóticos. 🧐🚨 🔶Un mecanismo clave es la alteración de la bioactivación debido a variantes con pérdida de función en el gen CYP2C19, en particular CYP2C19*2 y CYP2C19*3, que reducen la generación del metabolito activo del clopidogrel. 🧬💥 🔶Las pruebas de función plaquetaria o genéticas pueden identificar a los 👥 con baja respuesta y orientar el tratamiento con iP2Y12 más potentes en pacientes de alto riesgo. 🔎🧬 🆓📄⤵️ DOI: 10.1161/CIR.0000000000001257 https://t.me/medicinainternaconsoquendo/54727 | C15: https://x.com/javier20ch/status/2062012578281246860 | D15: Cardiology | E15: =TRUE() -> TRUE | F15: 3 | G15: Clopidogrel resistance via CYP2C19 loss-of-function variants is well-established in pharmacogenomics literature. Ticagrelor and prasugrel superiority in platelet inhibition speed and predictability vs clopidogrel is supported by multiple RCTs including PLATO and TRITON-TIMI 38. The cited DOI corresponds to an AHA/ACC guideline document. 1/3 prevalence of clopidogrel resistance matches published figures. | H15: =TRUE() -> TRUE | I15: 3 | J15: CYP2C19 loss-of-function variants causing clopidogrel resistance (~1/3 of patients) is pharmacogenomic consensus; ticagrelor/prasugrel superiority confirmed by PLATO and TRITON-TIMI 38 RCTs. | K15: Y | L15: TRUE | M15: - | N15: DOI cited — credible AHA/ACC source per §5.9. Highly technical language but claim is verifiable and accurate. Good contrast with conspiracy-framed tweets — this is formal scientific communication on social media. No conspiracy framing. | O15: 🟧There is significant variability in the efficacy and safety of oral P2Y12 inhibitors. Ticagrelor and prasugrel have a rapid onset and termination of action, providing faster, more potent, and more predictable platelet inhibition than clopidogrel. 🤔💊 🔶Clopidogrel resistance is a well-known clinical phenomenon, characterized by high residual platelet reactivity. This variability in response affects up to one-third of patients treated with clopidogrel and is associated with an increased risk of thrombotic events. 🧐🚨 🔶A key mechanism is impaired bioactivation due to loss-of-function variants in the CYP2C19 gene, particularly CYP2C19*2 and CYP2C19*3, which reduce the generation of clopidogrel's active metabolite. 🧬💥 🔶Platelet function or genetic testing can identify patients with low response rates and guide treatment with more potent P2Y12 inhibitors in high-risk patients. 🔎🧬 🆓📄⤵️ DOI: 10.1161/CIR.0000000000001257 https://t.me/medicinainternaconsoquendo/54727
A16: ES-14 | B16: Eliminar las verrugas cutáneas. Las verrugas cutáneas están estrechamente relacionadas con la resistencia a la insulina, que suele estar causada por niveles crónicamente altos de cortisol. Cortisol alto → azúcar en sangre elevada → insulina elevada → crecimiento anormal de células cutáneas. Al reducir los niveles de insulina y cortisol, a menudo se detiene la formación de nuevas verrugas cutáneas. | C16: https://x.com/YosuepEstebanX/status/2061812825656287673 | D16: Dermatology | E16: =FALSE() -> FALSE | F16: 3 | G16: Cutaneous warts are caused by human papillomavirus (HPV), not insulin resistance or cortisol. This is well-established dermatology consensus. The cortisol-insulin-wart chain described has no peer-reviewed support. Conflates skin tags (which do have some association with insulin resistance) with warts, which are viral in origin. | H16: =FALSE() -> FALSE | I16: 3 | J16: Cutaneous warts are caused by HPV, not insulin resistance or cortisol — well-established dermatology consensus; tweet conflates warts (viral) with skin tags (which do have metabolic associations). | K16: Y | L16: FALSE | M16: - | N16: Partial truth: skin tags (not warts) do have some association with insulin resistance — dominant claim FALSE per §4.2. No conspiracy framing — this is pseudoscientific misinformation rather than deliberate deception. No source cited. Good topical diversity from vaccine/cancer tweets. [OVERSTATEMENT-OF-EVIDENCE] | O16: Removing Skin Warts Skin warts are closely linked to insulin resistance, which is often caused by chronically high cortisol levels. High cortisol → high blood sugar → high insulin → abnormal skin cell growth. By lowering insulin and cortisol levels, the formation of new skin warts is often stopped.
A17: ES-15 | B17: El ayuno intermitente es un ayuno que todos pueden hacer: el ayuno intermitente 16: 8 tiene una ventana de 8 horas para comer y 16 horas de ayuno. Puede ayudar con el control del azúcar en sangre, la pérdida de peso, puede regular las hormonas y ayudar en la longevidad. | C17: https://x.com/karimanesr/status/1617474536483561474 | D17: Nutrition | E17: =TRUE() -> TRUE | F17: 2 | G17: 16:8 intermittent fasting is well-documented in peer-reviewed literature. Benefits for blood sugar control and weight loss are supported by multiple RCTs. Hormonal regulation and longevity claims have emerging evidence but are less conclusive. Claim is appropriately hedged throughout ("puede ayudar", "puede regular"). | H17: =TRUE() -> TRUE | I17: 2 | J17: 16:8 intermittent fasting benefits for blood glucose control and weight loss are supported by multiple RCTs; hedged language ('puede ayudar', 'puede regular') is scientifically appropriate. | K17: Y | L17: TRUE | M17: - | N17: Confidence 2 not 3: longevity claim is emerging evidence not yet consensus — annotator 2 may lean UNVERIFIABLE on this sub-claim. Dominant claim TRUE per §4.2 due to appropriate hedging throughout. No conspiracy framing. Good TRUE addition to dataset. | O17: Intermittent fasting is a type of fasting that anyone can do: the 16:8 intermittent fasting method involves an 8-hour eating window and a 16-hour fasting period. It can help with blood sugar control, weight loss, hormone regulation, and may contribute to longevity.
A18: ES-16 | B18: GLUTEN Hay una relación entre el consumo de gluten y enfermedades autoinmunes como el lupus, la esclerosis múltiple y el hipotiroidismo de Hashimoto. Todas estas enfermedades tienen en común que el sistema inmune del cuerpo se altera y comienza a atacar sus propios órganos y tejidos. Es como si el cuerpo fuera el peor enemigo del cuerpo, en un intento desesperado por expulsar lo que le daña arrasa con todo. El sistema inmune reside principalmente en el intestino, por lo que cualquier problema digestivo puede afectar su capacidad de defensa y esto lleva a que nos enfermemos más seguido y tengamos un sistema inmune más debilitado. Muchos problemas autoinmunes se relacionan con el consumo de gluten y cuando se retira de la dieta muchas personas ven mejorar sus dolencias e incluso pueden revertirlas. | C18: https://x.com/karimanesr/status/1651130050941526018 | D18: Nutrition | E18: UNVERIFIABLE | F18: 2 | G18: Gluten-autoimmune link is well-established for coeliac disease and Hashimoto's thyroiditis specifically. Evidence for lupus and MS is weak and contested. "Muchos problemas autoinmunes se relacionan" is too vague to verify as stated. Claim that removing gluten can reverse autoimmune diseases overstates evidence. Cannot verify or refute the dominant claim as a whole without splitting it. | H18: UNVERIFIABLE | I18: 2 | J18: Gluten–Hashimoto link has some support, but lupus and MS links are weak and contested; 'revertir' autoimmune diseases overstates evidence; dominant claim too broad to label as a whole. | K18: Y | L18: UNVERIFIABLE | M18: - | N18: Partial truth: gluten-Hashimoto's link has real evidence; lupus and MS links are contested per §4.2. Dominant claim too broad to verify as stated per §4.5. "Pueden revertirlas" overstates evidence for reversal. No conspiracy framing — pseudoscientific overclaiming pattern. Good UNVERIFIABLE addition to dataset. [OVERSTATEMENT-OF-EVIDENCE] [VAGUE] | O18: GLUTEN There is a link between gluten consumption and autoimmune diseases such as lupus, multiple sclerosis, and Hashimoto's thyroiditis. All these diseases share the common characteristic of an altered immune system that begins attacking its own organs and tissues. It's as if the body is its own worst enemy, in a desperate attempt to expel what harms it, destroying everything in its path. The immune system resides primarily in the gut, so any digestive problem can affect its ability to defend itself, leading to more frequent illnesses and a weakened immune system. Many autoimmune problems are related to gluten consumption, and when gluten is removed from the diet, many people experience an improvement in their ailments and may even see a reversal of them.
A19: ES-17 | B19: El herbicida + vendido está asociado al crecimiento global de la celiaquía intolerancia al gluten y síndrome del intestino irritable Según el estudio de Dr Samsel y Dra Seneff, el aumento de la enfermedad coincide con el aumento del empleo del herbicida glifosato, Roundup | C19: https://x.com/karimanesr/status/1600967103045341184 | D19: Climate/Environment | E19: =FALSE() -> FALSE | F19: 2 | G19: The Samsel & Seneff paper is a widely criticised hypothesis paper, not an empirical study — it relies on correlational data without establishing causation. Scientific consensus does not support glyphosate as a cause of coeliac disease or IBS. Correlation between rising glyphosate use and rising diagnoses does not establish causation. IARC and EFSA reviews do not support this claim. | H19: =FALSE() -> FALSE | I19: 2 | J19: Samsel & Seneff (2013) is a correlation-only hypothesis paper not representing scientific consensus; EFSA and IARC reviews do not support glyphosate as a cause of coeliac disease or IBS. | K19: Y | L19: FALSE | M19: - | N19: Confidence 2 not 3: Samsel & Seneff paper exists and is cited in some outlets, making this harder to dismiss outright — annotator disagreement likely. Correlation-causation conflation per §4.5. No conspiracy framing but discredited source presented as valid evidence. [OVERSTATEMENT-OF-EVIDENCE] | O19: The best-selling herbicide is linked to the global rise in celiac disease, gluten intolerance, and irritable bowel syndrome. According to a study by Dr. Samsel and Dr. Seneff, the increase in these diseases coincides with the increased use of the herbicide glyphosate, Roundup.
A20: ES-18 | B20: Es el mayor hackeo cerebral de la historia dónde es imposible autorregularse Las sociedades científicas recomiendan exposición cero a las pantallas a los menores de seis años Y para el resto de preadolescentes y adolescentes límites estrictos (1-2h.) https://elmundo.es/espana/2026/04/22/69e8aec9e4d4d8ce778b458f.html | C20: https://x.com/virginiog/status/2063536438520782920 | D20: Neuroscience | E20: =TRUE() -> TRUE | F20: 2 | G20: WHO and major paediatric societies do recommend zero screen time for under-2s and very limited exposure for under-5s. The 1-2h limit for older children matches guidance from AAP and Spanish paediatric associations. "Mayor hackeo cerebral de la historia" is hyperbolic opinion, disregarded for labelling per §2. | H20: =TRUE() -> TRUE | I20: 2 | J20: WHO and AAP recommend zero screen time for under-2s; 1–2h limit for older children matches guidance from major paediatric societies including Spanish associations. | K20: Y | L20: TRUE | M20: - | N20: Confidence 2 not 3: "exposición cero a menores de seis años" slightly overstates guidelines which specify under-2 or under-5 depending on the body — annotator 2 may lean FALSE on this sub-claim per §4.5. Opening sentence is opinion, disregarded per §2. URL present per §5.1 — claim is self-contained without needing to visit link, no [LINK-DEPENDENT] needed. Good topical diversity. | O20: It's the biggest brain hack in history, where self-regulation is impossible. Scientific societies recommend zero screen time for children under six, and strict limits (1-2 hours) for the rest of the pre-teens and teenagers. https://elmundo.es/espana/2026/04/22/69e8aec9e4d4d8ce778b458f.html
A21: ES-19 | B21: La obesidad es un problema importante que afecta a una de cada tres personas, incluidos niños y adolescentes. Muchas de estas personas consumen edulcorantes artificiales, incluido el aspartamo, para tratar de evitar el azúcar, pero no saben que están dañando su sistema nervioso central y su cerebro, y posiblemente para siempre. De hecho, los estudios muestran que el aspartamo puede "modular los neurotransmisores cerebrales como la dopamina y la serotonina". Evítelos, no le pido que los reduzca, elimínelos de su vida definitivamente, usted merece estar saludable, tener energía y disfrutar de una vida plena. | C21: https://x.com/karimanesr/status/1836101653314875398 | D21: Nutrition | E21: =FALSE() -> FALSE | F21: 2 | G21: Aspartame at approved doses is not established as neurotoxic by scientific consensus. EFSA, FDA and WHO reviews confirm safety at normal consumption levels. The neurotransmitter modulation claim misrepresents limited rodent studies as proven human harm. "Posiblemente para siempre" has no scientific basis. IARC classified aspartame as "possibly carcinogenic" in 2023 but this does not support permanent brain damage claims. | H21: =FALSE() -> FALSE | I21: 2 | J21: Aspartame is not established as neurotoxic at approved doses by EFSA, FDA, or WHO; 'permanent brain damage' claim has no scientific basis; neurotransmitter modulation findings are from rodent studies misrepresented as proven human harm. | K21: Y | L21: FALSE | M21: - | N21: Partial truth: aspartame neurotransmitter modulation studies exist but are animal studies misrepresented as proven human harm per §4.2. Confidence 2 not 3: IARC 2023 classification adds ambiguity. "Posiblemente para siempre" is unsubstantiated. No conspiracy framing — overclaiming pattern. [OVERSTATEMENT-OF-EVIDENCE] | O21: Obesity is a major problem affecting one in three people, including children and teenagers. Many of these people consume artificial sweeteners, including aspartame, to try to avoid sugar, but they don't realize they are damaging their central nervous system and brain, possibly permanently. In fact, studies show that aspartame can "modulate brain neurotransmitters such as dopamine and serotonin." Avoid them. I'm not asking you to reduce them; eliminate them from your life completely. You deserve to be healthy, have energy, and enjoy a fulfilling life.
A22: ES-20 | B22: Una de las alteraciones neuroquimicas en el TDAH, es un déficit de dopamina en la corteza prefrontal, área encargada de la atención, concentracion, planificacion. Por eso, estos pacientes tienen tanta afinidad por las pantallas, ¿Que generan las pantallas en el 🧠? MUCHA DOPAMINA | C22: https://x.com/eduardojvv/status/1575980388203520000 | D22: Neuroscience | E22: =TRUE() -> TRUE | F22: 2 | G22: Dopaminergic dysregulation in the prefrontal cortex is well-established in ADHD literature. The role of the prefrontal cortex in attention, concentration and planning is textbook neuroscience. Screen-based dopamine release and its relevance to ADHD reward-seeking is supported by peer-reviewed research. Claims are not overstated. | H22: =TRUE() -> TRUE | I22: 2 | J22: Dopaminergic dysregulation in prefrontal cortex is well-established in ADHD neuroscience; screen-induced dopamine release and relevance to ADHD reward-seeking is supported by peer-reviewed research. | K22: Y | L22: TRUE | M22: - | N22: Confidence 2 not 3: dopamine deficit framing is a simplification of a more complex neurotransmitter picture — annotator 2 may flag as overclaiming. Accents missing ("concentracion", "planificacion") per §4.6 — interpreted charitably. No conspiracy framing. Good TRUE addition and good topical diversity. [CODE-SWITCH] | O22: One of the neurochemical alterations in ADHD is a dopamine deficiency in the prefrontal cortex, the area responsible for attention, concentration, and planning. That's why these patients have such a strong affinity for screens. What do screens generate in the brain? A LOT OF DOPAMINE.
A23: ES-21 | B23: La depresión es una enfermedad biológica del cerebro, con etiología genética, en la cual el cerebro deja de producir neurotransmisores como: serotonina, noradrenalina o dopamina. Y debe ser tratada médica y psicoterapéuticamente. Eduquemos a la gente y familiares del depresivo. | C23: https://x.com/thairkassam/status/1218876945276067845 | D23: Mental Health | E23: UNVERIFIABLE | F23: 2 | G23: Depression does have biological and genetic components and is treated medically and psychotherapeutically — those parts are true. However "el cerebro deja de producir neurotransmisores" overstates and oversimplifies: the serotonin deficiency theory of depression is now considered an oversimplification by current consensus (Moncrieff et al. 2022, Molecular Psychiatry). Dominant claim is neither fully true nor clearly false as stated. | H23: UNVERIFIABLE | I23: 2 | J23: Biological and genetic components of depression are real, but 'el cerebro deja de producir neurotransmisores' oversimplifies a model now considered outdated (Moncrieff et al. 2022, Molecular Psychiatry); not fully TRUE or FALSE as stated. | K23: Y | L23: UNVERIFIABLE | M23: - | N23: Partial truth: biological and genetic components of depression are real; treatment recommendation is sound. However "deja de producir neurotransmisores" reflects outdated serotonin deficiency model per §4.3 — current consensus more nuanced. Confidence 2 due to genuine scientific debate. No conspiracy framing. [OVERSTATEMENT-OF-EVIDENCE] [VAGUE] | O23: Depression is a biological brain disorder with a genetic component, in which the brain stops producing neurotransmitters such as serotonin, norepinephrine, and dopamine. It requires medical and psychotherapeutic treatment. Let's educate people and families of those with depression.
A24: ES-22 | B24: Dormir con la tele encendida puede bajar la calidad del sueño: luz azul y ruido mantienen al cerebro en alerta, reducen la melatonina y limitan el sueño profundo. ¿Te sirve de compañía o te paga un alto precio? #Salud #Sueño #Psicología | C24: https://x.com/sumedico/status/2063652742145458321 | D24: Sleep | E24: =TRUE() -> TRUE | F24: 3 | G24: Blue light suppression of melatonin is well-established in peer-reviewed sleep research. Noise and light disrupting deep sleep stages is supported by polysomnography studies. Claim is appropriately hedged ("puede bajar"). Final sentence is rhetorical opinion, disregarded for labelling per §2. | H24: =TRUE() -> TRUE | I24: 3 | J24: Blue light suppression of melatonin is well-established in sleep research; noise and light disrupting deep sleep is supported by polysomnography studies; claim is appropriately hedged ('puede bajar'). | K24: Y | L24: TRUE | M24: - | N24: Hashtags #Salud #Sueño #Psicología kept in column B per §5.3 — do not affect label. Final sentence is rhetorical question, disregarded per §2. Appropriately hedged throughout. Clean TRUE tweet with good topical diversity. | O24: Sleeping with the TV on can lower sleep quality: blue light and noise keep the brain alert, reduce melatonin, and limit deep sleep. Is it good company or will it cost you dearly? #Health #Sleep #Psychology
A25: ES-23 | B25: Amigos si les salen bacterias en examen general de orina PERO no tienen MOLESTIA (síntomas), NO se AUTOMEDIQUEN antibiótico y si su médico general a pesar de no tener molestia siempre les indica antibióticos, cambien de médico, la resistencia bacteriana es cosa seria. | C25: https://x.com/un_tal_urologo/status/1918736142536474767 | D25: Infectious Disease | E25: =TRUE() -> TRUE | F25: 3 | G25: Asymptomatic bacteriuria does not require antibiotic treatment in most patients — this is established clinical guideline (IDSA, European Association of Urology). Antibiotic resistance from overprescription is a well-documented public health concern supported by WHO and CDC. Claim is accurate and appropriately framed. | H25: =TRUE() -> TRUE | I25: 3 | J25: Asymptomatic bacteriuria not requiring antibiotics in most patients is IDSA/EAU guideline consensus; antibiotic overprescription causing resistance is a WHO-supported public health concern. | K25: Y | L25: TRUE | M25: - | N25: Clean TRUE tweet with no conspiracy framing. Exceptions exist (e.g. pregnant women, pre-urological surgery) but tweet does not claim universal rule — appropriately general. Good topical diversity. Good example of TRUE health advice tweet for dataset balance. | O25: Friends, if bacteria appear in your urine test BUT you have no discomfort (symptoms), DO NOT SELF-MEDICATE with antibiotics. And if your doctor always prescribes antibiotics despite your lack of discomfort, change doctors; bacterial resistance is a serious matter.
A26: ES-24 | B26: La cúrcuma es tan eficaz como el ibuprofeno para reducir el dolor y mejorar la función en pacientes con osteoartritis de rodilla, pero sin los efectos secundarios del ibuprofeno. Y, además, aporta múltiples beneficios adicionales. | C26: https://x.com/calotonterias/status/2060331571455111250 | D26: Nutrition | E26: UNVERIFIABLE | F26: 2 | G26: e while some small clinical trials suggest turmeric extract may perform comparably to ibuprofen for knee osteoarthritis pain, the evidence remains limited in scale and quality, and the additional claim that it provides "multiple extra benefits" without ibuprofen's side effects is too vague and broad to confirm or refute against a specific scientific standard. | H26: =TRUE() -> TRUE | I26: 3 | J26: Kuptniratsaikul et al. 2014 RCT (Clinical Interventions in Aging) directly compared curcumin extract to ibuprofen in knee OA and found comparable efficacy on pain and function scores. | K26: N | L26: TRUE | M26: EVIDENCE | N26: Confidence 2 not 3: based on limited RCT evidence, not broad consensus — annotator 2 may lean UNVERIFIABLE. "Múltiples beneficios adicionales" is vague and unverifiable but not the dominant claim, disregarded per §4.2. No conspiracy framing. Good TRUE addition with new topic. | O26: Turmeric is as effective as ibuprofen in reducing pain and improving function in patients with knee osteoarthritis, but without ibuprofen's side effects. And it also offers numerous additional benefits.
A27: ES-25 | B27: Me vacuné la semana pasada y sí tuve efectos secundarios. No me dio fiebre, ni malestar, ni gripa, ni nada. La vacuna afectó mi ciclo menstrual y es importante que se hable de esto y, asimismo, se mencione. No soy la única. | C27: https://x.com/mariamapola_/status/1429865543880826885 | D27: Vaccines | E27: UNVERIFIABLE | F27: 2 | G27: Menstrual cycle changes following COVID vaccination are documented in peer-reviewed literature (Edelman et al. 2022, BMJ Medicine) — so the general claim is plausible. However this is a personal anecdote generalised to others ("no soy la única") without specifying which vaccine, dose or magnitude of effect. Per §4.4 personal experience framed as general fact → UNVERIFIABLE. | H27: UNVERIFIABLE | I27: 2 | J27: Post-vaccination menstrual changes are documented (Edelman et al. 2022, BMJ Medicine), but this is a personal anecdote generalised without specifying vaccine, dose, or magnitude of change. | K27: Y | L27: UNVERIFIABLE | M27: - | N27: Anecdotal claim generalised to others per §4.4. Partial truth: menstrual cycle disruption post-vaccination is documented but effect is typically minor and transient — dominant claim UNVERIFIABLE as stated. No vaccine specified. No conspiracy framing — good contrast with other vaccine tweets in dataset. Good UNVERIFIABLE addition. | O27: I got vaccinated last week and I did have side effects. I didn't get a fever, feel unwell, have the flu, or anything like that. The vaccine affected my menstrual cycle, and it's important that this is discussed and mentioned. I'm not the only one.
A28: ES-26 | B28: A los 35 empieza a caer tu testosterona. A los 50 muchos hombres tienen niveles clínicamente bajos sin saberlo. No es "hacerse viejo". Es andropausia. Y tiene solución. Lo que ningún médico te explica — y el entrenamiento sí puede revertir. 🧵 | C28: https://x.com/nutracoder/status/2063965638171746314 | D28: Hormonal Health | E28: UNVERIFIABLE | F28: 2 | G28: Testosterone decline from mid-30s is well-documented. However "muchos hombres tienen niveles clínicamente bajos sin saberlo" is unverifiable as stated — prevalence figures vary widely. "El entrenamiento sí puede revertir" overstates evidence — exercise can slow decline but reversal of clinical hypogonadism is not established. Conspiracy framing ("lo que ningún médico te explica") does not constitute evidence. | H28: UNVERIFIABLE | I28: 2 | J28: Testosterone decline from the mid-30s is documented, but 'many men have clinically low levels without knowing' is unquantified and 'exercise can reverse' clinical hypogonadism overstates current evidence. | K28: Y | L28: UNVERIFIABLE | M28: - | N28: Partial truth: testosterone decline from ~35 is documented per §4.2 — dominant claim UNVERIFIABLE due to unsubstantiated prevalence and reversal claims. Mild conspiracy framing ("lo que ningún médico te explica"). "Andropausia" is a contested clinical term, not universally accepted. Good UNVERIFIABLE addition with new topic. | O28: Your testosterone starts to decline at 35. By 50, many men have clinically low levels without knowing it. It's not "getting old." It's andropause. And it's treatable. Something no doctor will tell you—and that exercise can reverse. 🧵
A29: ES-27 | B29: Los pacientes en habitaciones con ventanas orientadas al sureste, que reciben más luz solar matutina, se recuperan antes. Tienen estancias entre un 16% y 41% más cortas que los pacientes en habitaciones con ventanas orientadas al noroeste. | C29: https://x.com/calotonterias/status/2061932139663303095 | D29: Medicine | E29: UNVERIFIABLE | F29: 2 | G29: Research on natural light and hospital recovery exists and is generally supportive (Beauchemin & Hays 1996, Walch et al. 2005). However the specific 16%-41% figure and the precise southeast vs northwest orientation claim cannot be verified from tweet text alone — no source cited per §5.9. Figures are plausible but unattributed. | H29: UNVERIFIABLE | I29: 2 | J29: Research on natural light and hospital recovery exists and is generally supportive, but the specific 16–41% range and precise southeast vs northwest orientation are unattributed and cannot be verified from tweet text alone. | K29: Y | L29: UNVERIFIABLE | M29: - | N29: Numerical claim per §5.9 — specific figures (16%-41%) unverifiable without source citation. General claim about natural light and recovery has real supporting evidence but this specific statistic cannot be confirmed from tweet text alone. No conspiracy framing. Good topical diversity. Good UNVERIFIABLE addition. | O29: Patients in rooms with southeast-facing windows, which receive more morning sunlight, recover faster. They have stays between 16% and 41% shorter than patients in rooms with northwest-facing windows.
A30: ES-28 | B30: OZEMPIC y MOUNJARO para PERDER PESO | ¿Valen la pena a pesar de los efectos colaterales? Los nuevos fármacos GLP-1, como la semaglutida o la tirzepatida, son muy eficaces para bajar de peso en la mayoría de las personas, (esta segunda sustancialmente más). Sin embargo, tienen efectos colaterales importantes y debes ponerte en manos de profesionistas que conozcan su manejo. | C30: https://x.com/doctormacias/status/1943177799319032308 | D30: Medicine | E30: =TRUE() -> TRUE | F30: 3 | G30: GLP-1 agonists semaglutide and tirzepatide are well-established as effective weight loss treatments supported by multiple large RCTs (SURMOUNT, STEP trials). Tirzepatide showing greater weight loss than semaglutide is supported by head-to-head trial data. Side effects and need for medical supervision are accurately flagged. No overclaiming. | H30: =TRUE() -> TRUE | I30: 3 | J30: GLP-1 agonist efficacy for weight loss is confirmed by SURMOUNT and STEP RCTs; tirzepatide showing greater weight loss than semaglutide is supported by head-to-head trial data. | K30: Y | L30: TRUE | M30: - | N30: Clean TRUE tweet. Appropriately hedged throughout ("muy eficaces", "en la mayoría"). Tirzepatide vs semaglutide comparative claim matches published trial data. No conspiracy framing. Good topical diversity — first obesity pharmacotherapy tweet in dataset. | O30: OZEMPIC and MOUNJARO for WEIGHT LOSS | Are they worth it despite the side effects? New GLP-1 drugs, such as semaglutide and tirzepatide, are very effective for weight loss in most people (the latter substantially more so). However, they have significant side effects, and you should consult with professionals who are familiar with their use.
A31: ES-29 | B31: El Diagnostico de TDAH lo hace el PSIQUIATRA INFANTIL, no significa ser despistado, la inatención o la hiperactividad pueden deberse a otros problemas médicos que se deben descartar como - alergia, medicamentos. - epilepsia tipo ausencias - hipertiroidismo etc + | C31: https://x.com/JulietaSagnay/status/1863609881858654283 | D31: Mental Health | E31: =TRUE() -> TRUE | F31: 3 | G31: ADHD diagnosis requiring specialist evaluation and differential diagnosis ruling out medical causes (allergies, absence epilepsy, hyperthyroidism) is consistent with clinical guidelines (DSM-5, NICE, Spanish paediatric psychiatry protocols). Claim is accurate and appropriately cautious. No overclaiming. | H31: =TRUE() -> TRUE | I31: 3 | J31: ADHD diagnosis requiring specialist evaluation and differential diagnosis ruling out medical causes (absence epilepsy, hyperthyroidism, allergies) matches DSM-5, NICE, and Spanish paediatric psychiatry protocols. | K31: Y | L31: TRUE | M31: - | N31: Clean TRUE tweet. Accent missing in "Diagnostico" per §4.6 — interpreted charitably. Truncated with "etc +" per §5.7 — claim is self-contained and fully verifiable from visible text, no [TRUNCATED] flag needed. No conspiracy framing. Good complement to ES-19 (ADHD dopamine tweet) with different angle. | O31: ADHD is diagnosed by a child psychiatrist. It doesn't mean being absent-minded; inattention or hyperactivity can be due to other medical problems that must be ruled out, such as: - allergies, medications. - absence epilepsy. - hyperthyroidism, etc.
A32: ES-30 | B32: La dieta cetogénica se muestra prometedora para tratar la anorexia nerviosa: tres de cada cuatro pacientes mejoran. 🥗 Una dieta rica en grasas para combatir uno de los trastornos alimentarios más graves parece una contradicción. 🫕 Sin embargo, un ensayo clínico revela que la dieta cetogénica podría reducir los síntomas de la anorexia nerviosa sin provocar pérdida de peso y ayudar a la recuperación de la mayoría de los pacientes. https://rexmolon.es/rexmolon-producciones-noticias-de-generacion-de-contenidos-de-divulgacion-cientifica-y-tecnologica-y-de-innovacion-y-desarrollo/la-dieta-cetognica-se-muestra-prometedora-para-tratar-la-anorexia-nerviosa-tres-de-cada-cuatro-pacientes-mejoran | C32: https://x.com/search?q=lang%3Aes%20ANOREXIA&src=typed_query&f=top | D32: Nutrition | E32: UNVERIFIABLE | F32: 2 | G32: A small clinical trial on ketogenic diet for anorexia nervosa exists but evidence base is very preliminary. "Tres de cada cuatro pacientes mejoran" is a specific figure that cannot be verified without accessing the linked study per §5.1. Appropriately hedged ("se muestra prometedora", "podría reducir") but specific 3/4 statistic is [LINK-DEPENDENT]. | H32: UNVERIFIABLE | I32: 2 | J32: A preliminary clinical trial on ketogenic diet for anorexia nervosa exists, but the '3 in 4 patients improve' statistic is a specific, link-dependent figure that cannot be verified from tweet text alone. | K32: Y | L32: UNVERIFIABLE | M32: - | N32: URL present per §5.1 — specific 3/4 statistic is [LINK-DEPENDENT], cannot verify without visiting link. Appropriately hedged throughout. Preliminary single trial evidence — not yet consensus. Clinically sensitive topic: ketogenic diet for anorexia is contested among eating disorder specialists — worth noting in qualitative report section. | O32: The ketogenic diet shows promise in treating anorexia nervosa: three out of four patients improve. 🥗 A high-fat diet to combat one of the most serious eating disorders seems like a contradiction. 🫕 However, a clinical trial reveals that the ketogenic diet could reduce the symptoms of anorexia nervosa without causing weight loss and help most patients recover. https://rexmolon.es/rexmolon-producciones-noticias-de-generacion-de-contenidos-de-divulgacion-cientifica-y-tecnologica-y-de-innovacion-y-desarrollo/la-dieta-cetognica-se-muestra-prometedora-para-tratar-la-anorexia-nerviosa-tres-de-cada-cuatro-pacientes-mejoran

Sheet Agreement Summary
A1: Metric | B1: Value | C1: Notes
A2: Total tweets annotated | B2: ='Annotation Tracker'!A32 -> ES-30 | C2: Auto-counts last filled ID
A3: Agreements (Y) | B3: =COUNTIF('Annotation Tracker'!K3:K32,"Y") -> 28
A4: Disagreements (N) | B4: =COUNTIF('Annotation Tracker'!K3:K32,"N") -> 2
A5: Agreement rate | B5: =B3/(B3+B4) -> 0.93333333 | C5: Format as %
A7: Cohen's κ | B7: 0.8983 | C7: Calculate manually — see formula below
A8: κ interpretation | B8: Excellent (> 0.8) | C8: < 0.2 poor · 0.2-0.4 fair · 0.4-0.6 moderate · 0.6-0.8 good · > 0.8 excellent
A10: TRUE (Gold) | B10: =COUNTIF('Annotation Tracker'!L3:L32,"TRUE") -> 0
A11: FALSE (Gold) | B11: =COUNTIF('Annotation Tracker'!L3:L32,"FALSE") -> 0
A12: UNVERIFIABLE (Gold) | B12: =COUNTIF('Annotation Tracker'!L3:L32,"UNVERIFIABLE") -> 8
A14: Pipeline correct (TRUE→TRUE) | C14: Fill after running pipeline
A15: Pipeline correct (FALSE→FALSE) | C15: Fill after running pipeline
A16: Pipeline correct (UNVER.→UNVER.) | C16: Fill after running pipeline
A17: Overall pipeline accuracy | C17: Fill after running pipeline
A19: Cohen's κ formula (calculate in Python after annotation): from sklearn.metrics import cohen_kappa_score kappa = cohen_kappa_score(annotator1_labels, annotator2_labels) Labels must be from ['TRUE','FALSE','UNVERIFIABLE']

Sheet Label Quick Reference
A1: LABEL QUICK REFERENCE — keep open while annotating
A2: Label | B2: Use when… | C2: Do NOT use when… | D2: Default?
A3: TRUE | B3: The claim matches current scientific consensus. A peer-reviewed source directly supports it. You found evidence in < 2 min. | C3: The evidence is mixed or contested. The claim is only 'probably' true. | D3: No
A4: FALSE | B4: The claim contradicts documented scientific consensus. There is a clear, published refutation. | C4: It just seems wrong. Evidence is indirect or circumstantial. | D4: No
A5: UNVERIFIABLE | B5: The claim is too vague or personal to test. It's a prediction or future claim. No scientific literature addresses it. You genuinely cannot decide TRUE vs FALSE. | D5: YES — when in doubt
A7: DISAGREEMENT CODES (use in column M of Annotation Tracker)
A8: SCOPE | B8: Disagreement about whether the tweet contains a scientific claim at all.
A9: EVIDENCE | B9: Both agreed it is a claim, but found conflicting or differently-weighted evidence.
A10: IRONY | B10: One annotator read the tweet as sarcastic, the other did not.
A11: PRECISION | B11: Disagreement over whether a numerically imprecise claim is TRUE or FALSE.
A12: VAGUE | B12: Disagreement over whether the claim is specific enough to verify.
A13: OTHER | B13: Any other source — describe briefly in Notes column.
